{
  "説明": "このファイルを編集して選手の能力値・名前・背番号などを変更できます",
  "能力値の範囲": "1～99（50が平均）",
  "バージョン": "1.0",
  "球団名": "Nagoya Sparks",
  "リーグ": "セントラル",
  "予算": 5000000000,
  "選手一覧": [
    {
      "名前": "市川悠",
      "背番号": 1,
      "年齢": 21,
      "ポジション": "投手",
      "外国人": false,
      "年俸": 74647692,
      "プロ年数": 0,
      "ドラフト順位": 0,
      "育成選手": false,
      "チームレベル": "一軍",
      "球種": "先発",
      "先発適性": 84,
      "中継ぎ適性": 36,
      "抑え適性": 43,
      "能力値": {
        "球速": 42,
        "コントロール": 48,
        "スタミナ": 69,
        "変化球": 53,
        "精神力": 57,
        "安定感": 50,
        "対左": 50,
        "持ち球": [
          "スライダー",
          "Hシンカー"
        ],
        "決め球": "スライダー",
        "球種レパートリー": {}
      }
    },
    {
      "名前": "木下翔",
      "背番号": 2,
      "年齢": 19,
      "ポジション": "投手",
      "外国人": false,
      "年俸": 80096153,
      "プロ年数": 0,
      "ドラフト順位": 0,
      "育成選手": false,
      "チームレベル": "一軍",
      "球種": "先発",
      "先発適性": 90,
      "中継ぎ適性": 55,
      "抑え適性": 39,
      "能力値": {
        "球速": 65,
        "コントロール": 65,
        "スタミナ": 48,
        "変化球": 46,
        "精神力": 56,
        "安定感": 50,
        "対左": 50,
        "持ち球": [
          "スライダー",
          "チェンジアップ"
        ],
        "決め球": "スライダー",
        "球種レパートリー": {}
      }
    },
    {
      "名前": "市川蒼",
      "背番号": 3,
      "年齢": 28,
      "ポジション": "投手",
      "外国人": false,
      "年俸": 88615384,
      "プロ年数": 0,
      "ドラフト順位": 0,
      "育成選手": false,
      "チームレベル": "一軍",
      "球種": "先発",
      "先発適性": 88,
      "中継ぎ適性": 46,
      "抑え適性": 36,
      "能力値": {
        "球速": 62,
        "コントロール": 71,
        "スタミナ": 44,
        "変化球": 57,
        "精神力": 41,
        "安定感": 50,
        "対左": 50,
        "持ち球": [
          "チェンジアップ",
          "シンカー"
        ],
        "決め球": "シンカー",
        "球種レパートリー": {}
      }
    },
    {
      "名前": "大川駿",
      "背番号": 4,
      "年齢": 20,
      "ポジション": "投手",
      "外国人": false,
      "年俸": 85200000,
      "プロ年数": 0,
      "ドラフト順位": 0,
      "育成選手": false,
      "チームレベル": "一軍",
      "球種": "先発",
      "先発適性": 91,
      "中継ぎ適性": 49,
      "抑え適性": 35,
      "能力値": {
        "球速": 75,
        "コントロール": 54,
        "スタミナ": 44,
        "変化球": 66,
        "精神力": 66,
        "安定感": 50,
        "対左": 50,
        "持ち球": [
          "スプリット",
          "スライダー",
          "カーブ",
          "シンカー"
        ],
        "決め球": "カーブ",
        "球種レパートリー": {}
      }
    },
    {
      "名前": "上田拓海",
      "背番号": 5,
      "年齢": 25,
      "ポジション": "投手",
      "外国人": false,
      "年俸": 88557692,
      "プロ年数": 0,
      "ドラフト順位": 0,
      "育成選手": false,
      "チームレベル": "一軍",
      "球種": "先発",
      "先発適性": 71,
      "中継ぎ適性": 57,
      "抑え適性": 44,
      "能力値": {
        "球速": 53,
        "コントロール": 70,
        "スタミナ": 43,
        "変化球": 71,
        "精神力": 53,
        "安定感": 50,
        "対左": 50,
        "持ち球": [
          "カーブ"
        ],
        "決め球": "カーブ",
        "球種レパートリー": {}
      }
    },
    {
      "名前": "篠原修平",
      "背番号": 6,
      "年齢": 36,
      "ポジション": "投手",
      "外国人": false,
      "年俸": 93735384,
      "プロ年数": 0,
      "ドラフト順位": 0,
      "育成選手": false,
      "チームレベル": "一軍",
      "球種": "先発",
      "先発適性": 79,
      "中継ぎ適性": 47,
      "抑え適性": 33,
      "能力値": {
        "球速": 40,
        "コントロール": 70,
        "スタミナ": 42,
        "変化球": 72,
        "精神力": 66,
        "安定感": 50,
        "対左": 50,
        "持ち球": [
          "スライダー",
          "スプリット"
        ],
        "決め球": "スプリット",
        "球種レパートリー": {}
      }
    },
    {
      "名前": "上田修平",
      "背番号": 7,
      "年齢": 26,
      "ポジション": "投手",
      "外国人": false,
      "年俸": 82772307,
      "プロ年数": 0,
      "ドラフト順位": 0,
      "育成選手": false,
      "チームレベル": "一軍",
      "球種": "先発",
      "先発適性": 70,
      "中継ぎ適性": 54,
      "抑え適性": 43,
      "能力値": {
        "球速": 44,
        "コントロール": 47,
        "スタミナ": 71,
        "変化球": 75,
        "精神力": 37,
        "安定感": 50,
        "対左": 50,
        "持ち球": [
          "スライダー",
          "チェンジアップ",
          "スプリット"
        ],
        "決め球": "チェンジアップ",
        "球種レパートリー": {}
      }
    },
    {
      "名前": "大川大輝",
      "背番号": 8,
      "年齢": 27,
      "ポジション": "投手",
      "外国人": false,
      "年俸": 89583846,
      "プロ年数": 0,
      "ドラフト順位": 0,
      "育成選手": false,
      "チームレベル": "一軍",
      "球種": "先発",
      "先発適性": 96,
      "中継ぎ適性": 46,
      "抑え適性": 29,
      "能力値": {
        "球速": 74,
        "コントロール": 46,
        "スタミナ": 62,
        "変化球": 68,
        "精神力": 53,
        "安定感": 50,
        "対左": 50,
        "持ち球": [
          "ツーシーム",
          "スプリット",
          "フォーク"
        ],
        "決め球": "ツーシーム",
        "球種レパートリー": {}
      }
    },
    {
      "名前": "木下陽太",
      "背番号": 9,
      "年齢": 30,
      "ポジション": "投手",
      "外国人": false,
      "年俸": 79700000,
      "プロ年数": 0,
      "ドラフト順位": 0,
      "育成選手": false,
      "チームレベル": "一軍",
      "球種": "中継ぎ",
      "先発適性": 29,
      "中継ぎ適性": 81,
      "抑え適性": 67,
      "能力値": {
        "球速": 40,
        "コントロール": 55,
        "スタミナ": 47,
        "変化球": 61,
        "精神力": 50,
        "安定感": 50,
        "対左": 50,
        "持ち球": [
          "スライダー",
          "ツーシーム",
          "カットボール",
          "カーブ",
          "Hシンカー"
        ],
        "決め球": "カーブ",
        "球種レパートリー": {}
      }
    },
    {
      "名前": "笹本樹",
      "背番号": 10,
      "年齢": 30,
      "ポジション": "投手",
      "外国人": false,
      "年俸": 81300000,
      "プロ年数": 0,
      "ドラフト順位": 0,
      "育成選手": false,
      "チームレベル": "一軍",
      "球種": "中継ぎ",
      "先発適性": 27,
      "中継ぎ適性": 99,
      "抑え適性": 56,
      "能力値": {
        "球速": 40,
        "コントロール": 55,
        "スタミナ": 48,
        "変化球": 68,
        "精神力": 43,
        "安定感": 50,
        "対左": 50,
        "持ち球": [
          "スライダー",
          "カットボール",
          "カーブ"
        ],
        "決め球": "カットボール",
        "球種レパートリー": {}
      }
    },
    {
      "名前": "国分拓海",
      "背番号": 11,
      "年齢": 26,
      "ポジション": "投手",
      "外国人": false,
      "年俸": 92949230,
      "プロ年数": 0,
      "ドラフト順位": 0,
      "育成選手": false,
      "チームレベル": "一軍",
      "球種": "中継ぎ",
      "先発適性": 50,
      "中継ぎ適性": 70,
      "抑え適性": 67,
      "能力値": {
        "球速": 51,
        "コントロール": 75,
        "スタミナ": 45,
        "変化球": 74,
        "精神力": 64,
        "安定感": 50,
        "対左": 50,
        "持ち球": [
          "スライダー",
          "シュート",
          "フォーク"
        ],
        "決め球": "シュート",
        "球種レパートリー": {}
      }
    },
    {
      "名前": "池上健",
      "背番号": 12,
      "年齢": 36,
      "ポジション": "投手",
      "外国人": false,
      "年俸": 88713846,
      "プロ年数": 0,
      "ドラフト順位": 0,
      "育成選手": false,
      "チームレベル": "一軍",
      "球種": "中継ぎ",
      "先発適性": 20,
      "中継ぎ適性": 70,
      "抑え適性": 50,
      "能力値": {
        "球速": 41,
        "コントロール": 61,
        "スタミナ": 53,
        "変化球": 61,
        "精神力": 62,
        "安定感": 50,
        "対左": 50,
        "持ち球": [
          "ツーシーム",
          "スライダー",
          "カーブ",
          "スプリット"
        ],
        "決め球": "スライダー",
        "球種レパートリー": {}
      }
    },
    {
      "名前": "倉田駿",
      "背番号": 13,
      "年齢": 35,
      "ポジション": "投手",
      "外国人": false,
      "年俸": 95123076,
      "プロ年数": 0,
      "ドラフト順位": 0,
      "育成選手": false,
      "チームレベル": "一軍",
      "球種": "中継ぎ",
      "先発適性": 38,
      "中継ぎ適性": 80,
      "抑え適性": 52,
      "能力値": {
        "球速": 58,
        "コントロール": 66,
        "スタミナ": 54,
        "変化球": 65,
        "精神力": 45,
        "安定感": 50,
        "対左": 50,
        "持ち球": [
          "パーム",
          "チェンジアップ",
          "フォーク"
        ],
        "決め球": "フォーク",
        "球種レパートリー": {}
      }
    },
    {
      "名前": "荒木勇人",
      "背番号": 14,
      "年齢": 25,
      "ポジション": "投手",
      "外国人": false,
      "年俸": 80576923,
      "プロ年数": 0,
      "ドラフト順位": 0,
      "育成選手": false,
      "チームレベル": "一軍",
      "球種": "中継ぎ",
      "先発適性": 33,
      "中継ぎ適性": 76,
      "抑え適性": 64,
      "能力値": {
        "球速": 52,
        "コントロール": 52,
        "スタミナ": 72,
        "変化球": 51,
        "精神力": 47,
        "安定感": 50,
        "対左": 50,
        "持ち球": [
          "チェンジアップ",
          "カットボール",
          "カーブ"
        ],
        "決め球": "カーブ",
        "球種レパートリー": {}
      }
    },
    {
      "名前": "岡崎颯太",
      "背番号": 15,
      "年齢": 26,
      "ポジション": "投手",
      "外国人": false,
      "年俸": 82093846,
      "プロ年数": 0,
      "ドラフト順位": 0,
      "育成選手": false,
      "チームレベル": "一軍",
      "球種": "中継ぎ",
      "先発適性": 44,
      "中継ぎ適性": 77,
      "抑え適性": 65,
      "能力値": {
        "球速": 58,
        "コントロール": 59,
        "スタミナ": 55,
        "変化球": 53,
        "精神力": 38,
        "安定感": 50,
        "対左": 50,
        "持ち球": [
          "チェンジアップ",
          "カットボール"
        ],
        "決め球": "チェンジアップ",
        "球種レパートリー": {}
      }
    },
    {
      "名前": "岩崎智也",
      "背番号": 16,
      "年齢": 20,
      "ポジション": "投手",
      "外国人": false,
      "年俸": 83630769,
      "プロ年数": 0,
      "ドラフト順位": 0,
      "育成選手": false,
      "チームレベル": "一軍",
      "球種": "中継ぎ",
      "先発適性": 39,
      "中継ぎ適性": 92,
      "抑え適性": 44,
      "能力値": {
        "球速": 67,
        "コントロール": 59,
        "スタミナ": 45,
        "変化球": 65,
        "精神力": 54,
        "安定感": 50,
        "対左": 50,
        "持ち球": [
          "スライダー",
          "カーブ"
        ],
        "決め球": "スライダー",
        "球種レパートリー": {}
      }
    },
    {
      "名前": "島田翔太",
      "背番号": 17,
      "年齢": 29,
      "ポジション": "投手",
      "外国人": false,
      "年俸": 89208461,
      "プロ年数": 0,
      "ドラフト順位": 0,
      "育成選手": false,
      "チームレベル": "一軍",
      "球種": "中継ぎ",
      "先発適性": 34,
      "中継ぎ適性": 74,
      "抑え適性": 63,
      "能力値": {
        "球速": 63,
        "コントロール": 57,
        "スタミナ": 64,
        "変化球": 62,
        "精神力": 38,
        "安定感": 50,
        "対左": 50,
        "持ち球": [
          "ツーシーム",
          "スライダー",
          "フォーク"
        ],
        "決め球": "ツーシーム",
        "球種レパートリー": {}
      }
    },
    {
      "名前": "赤井龍馬",
      "背番号": 18,
      "年齢": 28,
      "ポジション": "投手",
      "外国人": false,
      "年俸": 72270769,
      "プロ年数": 0,
      "ドラフト順位": 0,
      "育成選手": false,
      "チームレベル": "一軍",
      "球種": "中継ぎ",
      "先発適性": 26,
      "中継ぎ適性": 90,
      "抑え適性": 58,
      "能力値": {
        "球速": 49,
        "コントロール": 44,
        "スタミナ": 48,
        "変化球": 47,
        "精神力": 44,
        "安定感": 50,
        "対左": 50,
        "持ち球": [
          "チェンジアップ",
          "カーブ"
        ],
        "決め球": "カーブ",
        "球種レパートリー": {}
      }
    },
    {
      "名前": "岩崎龍馬",
      "背番号": 19,
      "年齢": 38,
      "ポジション": "投手",
      "外国人": false,
      "年俸": 95007692,
      "プロ年数": 0,
      "ドラフト順位": 0,
      "育成選手": false,
      "チームレベル": "一軍",
      "球種": "中継ぎ",
      "先発適性": 47,
      "中継ぎ適性": 96,
      "抑え適性": 59,
      "能力値": {
        "球速": 53,
        "コントロール": 71,
        "スタミナ": 66,
        "変化球": 51,
        "精神力": 37,
        "安定感": 50,
        "対左": 50,
        "持ち球": [
          "ツーシーム",
          "カーブ",
          "スプリット"
        ],
        "決め球": "スプリット",
        "球種レパートリー": {}
      }
    },
    {
      "名前": "尾崎颯太",
      "背番号": 20,
      "年齢": 24,
      "ポジション": "投手",
      "外国人": false,
      "年俸": 88040000,
      "プロ年数": 0,
      "ドラフト順位": 0,
      "育成選手": false,
      "チームレベル": "一軍",
      "球種": "中継ぎ",
      "先発適性": 20,
      "中継ぎ適性": 74,
      "抑え適性": 45,
      "能力値": {
        "球速": 71,
        "コントロール": 52,
        "スタミナ": 58,
        "変化球": 64,
        "精神力": 64,
        "安定感": 50,
        "対左": 50,
        "持ち球": [
          "チェンジアップ"
        ],
        "決め球": "チェンジアップ",
        "球種レパートリー": {}
      }
    },
    {
      "名前": "国分康平",
      "背番号": 21,
      "年齢": 26,
      "ポジション": "投手",
      "外国人": false,
      "年俸": 84420000,
      "プロ年数": 0,
      "ドラフト順位": 0,
      "育成選手": false,
      "チームレベル": "一軍",
      "球種": "中継ぎ",
      "先発適性": 35,
      "中継ぎ適性": 80,
      "抑え適性": 62,
      "能力値": {
        "球速": 69,
        "コントロール": 47,
        "スタミナ": 75,
        "変化球": 46,
        "精神力": 58,
        "安定感": 50,
        "対左": 50,
        "持ち球": [
          "スライダー",
          "Hシンカー",
          "カーブ"
        ],
        "決め球": "Hシンカー",
        "球種レパートリー": {}
      }
    },
    {
      "名前": "竹内修平",
      "背番号": 22,
      "年齢": 35,
      "ポジション": "投手",
      "外国人": false,
      "年俸": 97303846,
      "プロ年数": 0,
      "ドラフト順位": 0,
      "育成選手": false,
      "チームレベル": "一軍",
      "球種": "中継ぎ",
      "先発適性": 28,
      "中継ぎ適性": 91,
      "抑え適性": 62,
      "能力値": {
        "球速": 41,
        "コントロール": 73,
        "スタミナ": 62,
        "変化球": 73,
        "精神力": 49,
        "安定感": 50,
        "対左": 50,
        "持ち球": [
          "スライダー",
          "Hシンカー",
          "カーブ"
        ],
        "決め球": "カーブ",
        "球種レパートリー": {}
      }
    },
    {
      "名前": "島田隼人",
      "背番号": 23,
      "年齢": 33,
      "ポジション": "投手",
      "外国人": false,
      "年俸": 92076923,
      "プロ年数": 0,
      "ドラフト順位": 0,
      "育成選手": false,
      "チームレベル": "一軍",
      "球種": "抑え",
      "先発適性": 11,
      "中継ぎ適性": 61,
      "抑え適性": 80,
      "能力値": {
        "球速": 61,
        "コントロール": 50,
        "スタミナ": 70,
        "変化球": 68,
        "精神力": 43,
        "安定感": 50,
        "対左": 50,
        "持ち球": [
          "縦スライダー",
          "スライダー",
          "シュート",
          "フォーク",
          "ツーシーム",
          "シンカー"
        ],
        "決め球": "スライダー",
        "球種レパートリー": {}
      }
    },
    {
      "名前": "片桐亮太",
      "背番号": 24,
      "年齢": 32,
      "ポジション": "投手",
      "外国人": false,
      "年俸": 88033846,
      "プロ年数": 0,
      "ドラフト順位": 0,
      "育成選手": false,
      "チームレベル": "一軍",
      "球種": "抑え",
      "先発適性": 13,
      "中継ぎ適性": 58,
      "抑え適性": 94,
      "能力値": {
        "球速": 49,
        "コントロール": 72,
        "スタミナ": 42,
        "変化球": 53,
        "精神力": 59,
        "安定感": 50,
        "対左": 50,
        "持ち球": [
          "シュート",
          "カーブ"
        ],
        "決め球": "シュート",
        "球種レパートリー": {}
      }
    },
    {
      "名前": "天野圭介",
      "背番号": 25,
      "年齢": 18,
      "ポジション": "投手",
      "外国人": false,
      "年俸": 81692307,
      "プロ年数": 0,
      "ドラフト順位": 0,
      "育成選手": false,
      "チームレベル": "一軍",
      "球種": "抑え",
      "先発適性": 35,
      "中継ぎ適性": 51,
      "抑え適性": 84,
      "能力値": {
        "球速": 56,
        "コントロール": 64,
        "スタミナ": 46,
        "変化球": 62,
        "精神力": 68,
        "安定感": 50,
        "対左": 50,
        "持ち球": [
          "スライダー",
          "カーブ",
          "スプリット",
          "縦カーブ",
          "シンカー"
        ],
        "決め球": "スプリット",
        "球種レパートリー": {}
      }
    },
    {
      "名前": "秋元慎太郎",
      "背番号": 26,
      "年齢": 24,
      "ポジション": "投手",
      "外国人": false,
      "年俸": 76021538,
      "プロ年数": 0,
      "ドラフト順位": 0,
      "育成選手": false,
      "チームレベル": "一軍",
      "球種": "抑え",
      "先発適性": 21,
      "中継ぎ適性": 74,
      "抑え適性": 87,
      "能力値": {
        "球速": 59,
        "コントロール": 40,
        "スタミナ": 54,
        "変化球": 62,
        "精神力": 36,
        "安定感": 50,
        "対左": 50,
        "持ち球": [
          "ツーシーム",
          "スプリット",
          "フォーク"
        ],
        "決め球": "フォーク",
        "球種レパートリー": {}
      }
    },
    {
      "名前": "市川優",
      "背番号": 27,
      "年齢": 30,
      "ポジション": "投手",
      "外国人": false,
      "年俸": 90000000,
      "プロ年数": 0,
      "ドラフト順位": 0,
      "育成選手": false,
      "チームレベル": "一軍",
      "球種": "抑え",
      "先発適性": 36,
      "中継ぎ適性": 65,
      "抑え適性": 94,
      "能力値": {
        "球速": 71,
        "コントロール": 44,
        "スタミナ": 60,
        "変化球": 68,
        "精神力": 57,
        "安定感": 50,
        "対左": 50,
        "持ち球": [
          "スライダー",
          "カーブ"
        ],
        "決め球": "カーブ",
        "球種レパートリー": {}
      }
    },
    {
      "名前": "金子隼人",
      "背番号": 28,
      "年齢": 31,
      "ポジション": "投手",
      "外国人": false,
      "年俸": 92909230,
      "プロ年数": 0,
      "ドラフト順位": 0,
      "育成選手": false,
      "チームレベル": "一軍",
      "球種": "抑え",
      "先発適性": 25,
      "中継ぎ適性": 63,
      "抑え適性": 98,
      "能力値": {
        "球速": 68,
        "コントロール": 57,
        "スタミナ": 75,
        "変化球": 56,
        "精神力": 42,
        "安定感": 50,
        "対左": 50,
        "持ち球": [
          "縦カーブ",
          "カーブ"
        ],
        "決め球": "カーブ",
        "球種レパートリー": {}
      }
    },
    {
      "名前": "柴田大輝",
      "背番号": 29,
      "年齢": 21,
      "ポジション": "捕手",
      "外国人": false,
      "年俸": 90629000,
      "プロ年数": 0,
      "ドラフト順位": 0,
      "育成選手": false,
      "チームレベル": "一軍",
      "サブポジション": [],
      "サブポジション評価": {},
      "能力値": {
        "ミート": 73,
        "パワー": 68,
        "走力": 55,
        "肩力": 64,
        "守備": 65,
        "捕球": 67,
        "精神力": 59,
        "勝負強さ": 43,
        "安定感": 31,
        "対左": 50,
        "代打": 50,
        "盗塁": 50,
        "走塁": 50,
        "弾道": 2
      }
    },
    {
      "名前": "大野智也",
      "背番号": 30,
      "年齢": 28,
      "ポジション": "捕手",
      "外国人": false,
      "年俸": 78336000,
      "プロ年数": 0,
      "ドラフト順位": 0,
      "育成選手": false,
      "チームレベル": "一軍",
      "サブポジション": [],
      "サブポジション評価": {},
      "能力値": {
        "ミート": 46,
        "パワー": 58,
        "走力": 47,
        "肩力": 42,
        "守備": 68,
        "捕球": 38,
        "精神力": 33,
        "勝負強さ": 60,
        "安定感": 50,
        "対左": 50,
        "代打": 50,
        "盗塁": 50,
        "走塁": 50,
        "弾道": 2
      }
    },
    {
      "名前": "佐久間悠",
      "背番号": 31,
      "年齢": 22,
      "ポジション": "捕手",
      "外国人": false,
      "年俸": 85644000,
      "プロ年数": 0,
      "ドラフト順位": 0,
      "育成選手": false,
      "チームレベル": "一軍",
      "サブポジション": [
        "一塁手"
      ],
      "サブポジション評価": {
        "一塁手": 0.6509553025587331
      },
      "能力値": {
        "ミート": 53,
        "パワー": 68,
        "走力": 66,
        "肩力": 38,
        "守備": 66,
        "捕球": 47,
        "精神力": 47,
        "勝負強さ": 54,
        "安定感": 54,
        "対左": 50,
        "代打": 50,
        "盗塁": 50,
        "走塁": 50,
        "弾道": 2
      }
    },
    {
      "名前": "滝沢陸",
      "背番号": 32,
      "年齢": 23,
      "ポジション": "捕手",
      "外国人": false,
      "年俸": 90159000,
      "プロ年数": 0,
      "ドラフト順位": 0,
      "育成選手": false,
      "チームレベル": "二軍",
      "サブポジション": [],
      "サブポジション評価": {},
      "能力値": {
        "ミート": 57,
        "パワー": 67,
        "走力": 73,
        "肩力": 36,
        "守備": 52,
        "捕球": 38,
        "精神力": 65,
        "勝負強さ": 58,
        "安定感": 48,
        "対左": 50,
        "代打": 50,
        "盗塁": 50,
        "走塁": 50,
        "弾道": 2
      }
    },
    {
      "名前": "江藤隼人",
      "背番号": 33,
      "年齢": 35,
      "ポジション": "一塁手",
      "外国人": false,
      "年俸": 90180000,
      "プロ年数": 0,
      "ドラフト順位": 0,
      "育成選手": false,
      "チームレベル": "二軍",
      "サブポジション": [
        "外野手"
      ],
      "サブポジション評価": {
        "外野手": 0.6377296986764396
      },
      "能力値": {
        "ミート": 63,
        "パワー": 41,
        "走力": 75,
        "肩力": 36,
        "守備": 60,
        "捕球": 43,
        "精神力": 61,
        "勝負強さ": 43,
        "安定感": 62,
        "対左": 50,
        "代打": 50,
        "盗塁": 50,
        "走塁": 50,
        "弾道": 2
      }
    },
    {
      "名前": "有馬康平",
      "背番号": 34,
      "年齢": 30,
      "ポジション": "一塁手",
      "外国人": false,
      "年俸": 103610000,
      "プロ年数": 0,
      "ドラフト順位": 0,
      "育成選手": false,
      "チームレベル": "二軍",
      "サブポジション": [
        "三塁手"
      ],
      "サブポジション評価": {
        "三塁手": 0.5979588363608109
      },
      "能力値": {
        "ミート": 72,
        "パワー": 71,
        "走力": 66,
        "肩力": 60,
        "守備": 66,
        "捕球": 37,
        "精神力": 34,
        "勝負強さ": 64,
        "安定感": 33,
        "対左": 50,
        "代打": 50,
        "盗塁": 50,
        "走塁": 50,
        "弾道": 3
      }
    },
    {
      "名前": "北村大和",
      "背番号": 35,
      "年齢": 22,
      "ポジション": "一塁手",
      "外国人": false,
      "年俸": 97111999,
      "プロ年数": 0,
      "ドラフト順位": 0,
      "育成選手": false,
      "チームレベル": "二軍",
      "サブポジション": [
        "三塁手"
      ],
      "サブポジション評価": {
        "三塁手": 0.6970643832085557
      },
      "能力値": {
        "ミート": 72,
        "パワー": 69,
        "走力": 72,
        "肩力": 44,
        "守備": 46,
        "捕球": 35,
        "精神力": 61,
        "勝負強さ": 57,
        "安定感": 56,
        "対左": 50,
        "代打": 50,
        "盗塁": 50,
        "走塁": 50,
        "弾道": 2
      }
    },
    {
      "名前": "坂井海斗",
      "背番号": 36,
      "年齢": 22,
      "ポジション": "一塁手",
      "外国人": false,
      "年俸": 82472000,
      "プロ年数": 0,
      "ドラフト順位": 0,
      "育成選手": false,
      "チームレベル": "二軍",
      "サブポジション": [],
      "サブポジション評価": {},
      "能力値": {
        "ミート": 51,
        "パワー": 69,
        "走力": 49,
        "肩力": 65,
        "守備": 55,
        "捕球": 48,
        "精神力": 36,
        "勝負強さ": 67,
        "安定感": 40,
        "対左": 50,
        "代打": 50,
        "盗塁": 50,
        "走塁": 50,
        "弾道": 2
      }
    },
    {
      "名前": "黒田翼",
      "背番号": 37,
      "年齢": 24,
      "ポジション": "一塁手",
      "外国人": false,
      "年俸": 79608000,
      "プロ年数": 0,
      "ドラフト順位": 0,
      "育成選手": false,
      "チームレベル": "二軍",
      "サブポジション": [],
      "サブポジション評価": {},
      "能力値": {
        "ミート": 43,
        "パワー": 59,
        "走力": 64,
        "肩力": 40,
        "守備": 60,
        "捕球": 38,
        "精神力": 45,
        "勝負強さ": 65,
        "安定感": 34,
        "対左": 50,
        "代打": 50,
        "盗塁": 50,
        "走塁": 50,
        "弾道": 3
      }
    },
    {
      "名前": "岩崎陽太",
      "背番号": 38,
      "年齢": 24,
      "ポジション": "二塁手",
      "外国人": false,
      "年俸": 85188000,
      "プロ年数": 0,
      "ドラフト順位": 0,
      "育成選手": false,
      "チームレベル": "二軍",
      "サブポジション": [
        "遊撃手",
        "三塁手"
      ],
      "サブポジション評価": {
        "遊撃手": 0.7937742800904894,
        "三塁手": 0.6119238437221485
      },
      "能力値": {
        "ミート": 71,
        "パワー": 36,
        "走力": 70,
        "肩力": 61,
        "守備": 44,
        "捕球": 51,
        "精神力": 30,
        "勝負強さ": 55,
        "安定感": 33,
        "対左": 50,
        "代打": 50,
        "盗塁": 50,
        "走塁": 50,
        "弾道": 2
      }
    },
    {
      "名前": "竹内大輝",
      "背番号": 39,
      "年齢": 30,
      "ポジション": "二塁手",
      "外国人": false,
      "年俸": 88920000,
      "プロ年数": 0,
      "ドラフト順位": 0,
      "育成選手": false,
      "チームレベル": "二軍",
      "サブポジション": [
        "三塁手"
      ],
      "サブポジション評価": {
        "三塁手": 0.5730296533901358
      },
      "能力値": {
        "ミート": 73,
        "パワー": 44,
        "走力": 48,
        "肩力": 65,
        "守備": 70,
        "捕球": 36,
        "精神力": 35,
        "勝負強さ": 64,
        "安定感": 38,
        "対左": 50,
        "代打": 50,
        "盗塁": 50,
        "走塁": 50,
        "弾道": 1
      }
    },
    {
      "名前": "遠藤海斗",
      "背番号": 40,
      "年齢": 28,
      "ポジション": "二塁手",
      "外国人": false,
      "年俸": 76928000,
      "プロ年数": 0,
      "ドラフト順位": 0,
      "育成選手": false,
      "チームレベル": "二軍",
      "サブポジション": [
        "遊撃手"
      ],
      "サブポジション評価": {
        "遊撃手": 0.8021077748795212
      },
      "能力値": {
        "ミート": 52,
        "パワー": 44,
        "走力": 51,
        "肩力": 47,
        "守備": 54,
        "捕球": 59,
        "精神力": 59,
        "勝負強さ": 59,
        "安定感": 56,
        "対左": 50,
        "代打": 50,
        "盗塁": 50,
        "走塁": 50,
        "弾道": 2
      }
    },
    {
      "名前": "佐久間駿",
      "背番号": 41,
      "年齢": 21,
      "ポジション": "二塁手",
      "外国人": false,
      "年俸": 79134000,
      "プロ年数": 0,
      "ドラフト順位": 0,
      "育成選手": false,
      "チームレベル": "二軍",
      "サブポジション": [],
      "サブポジション評価": {},
      "能力値": {
        "ミート": 55,
        "パワー": 50,
        "走力": 57,
        "肩力": 54,
        "守備": 51,
        "捕球": 60,
        "精神力": 41,
        "勝負強さ": 70,
        "安定感": 64,
        "対左": 50,
        "代打": 50,
        "盗塁": 50,
        "走塁": 50,
        "弾道": 3
      }
    },
    {
      "名前": "坂井駿",
      "背番号": 42,
      "年齢": 33,
      "ポジション": "二塁手",
      "外国人": false,
      "年俸": 66766000,
      "プロ年数": 0,
      "ドラフト順位": 0,
      "育成選手": false,
      "チームレベル": "二軍",
      "サブポジション": [
        "遊撃手"
      ],
      "サブポジション評価": {
        "遊撃手": 0.7338292850231889
      },
      "能力値": {
        "ミート": 41,
        "パワー": 39,
        "走力": 39,
        "肩力": 70,
        "守備": 54,
        "捕球": 60,
        "精神力": 52,
        "勝負強さ": 43,
        "安定感": 30,
        "対左": 50,
        "代打": 50,
        "盗塁": 50,
        "走塁": 50,
        "弾道": 1
      }
    },
    {
      "名前": "桜井匠",
      "背番号": 43,
      "年齢": 27,
      "ポジション": "二塁手",
      "外国人": false,
      "年俸": 65659000,
      "プロ年数": 0,
      "ドラフト順位": 0,
      "育成選手": false,
      "チームレベル": "二軍",
      "サブポジション": [
        "三塁手"
      ],
      "サブポジション評価": {
        "三塁手": 0.6246754668066534
      },
      "能力値": {
        "ミート": 41,
        "パワー": 39,
        "走力": 48,
        "肩力": 54,
        "守備": 40,
        "捕球": 39,
        "精神力": 62,
        "勝負強さ": 40,
        "安定感": 30,
        "対左": 50,
        "代打": 50,
        "盗塁": 50,
        "走塁": 50,
        "弾道": 1
      }
    },
    {
      "名前": "関根陽翔",
      "背番号": 44,
      "年齢": 36,
      "ポジション": "三塁手",
      "外国人": false,
      "年俸": 96423999,
      "プロ年数": 0,
      "ドラフト順位": 0,
      "育成選手": false,
      "チームレベル": "二軍",
      "サブポジション": [],
      "サブポジション評価": {},
      "能力値": {
        "ミート": 58,
        "パワー": 65,
        "走力": 75,
        "肩力": 40,
        "守備": 51,
        "捕球": 54,
        "精神力": 31,
        "勝負強さ": 32,
        "安定感": 34,
        "対左": 50,
        "代打": 50,
        "盗塁": 50,
        "走塁": 50,
        "弾道": 2
      }
    },
    {
      "名前": "大石陽翔",
      "背番号": 45,
      "年齢": 19,
      "ポジション": "三塁手",
      "外国人": false,
      "年俸": 82586000,
      "プロ年数": 0,
      "ドラフト順位": 0,
      "育成選手": false,
      "チームレベル": "二軍",
      "サブポジション": [
        "遊撃手"
      ],
      "サブポジション評価": {
        "遊撃手": 0.5833463747811504
      },
      "能力値": {
        "ミート": 63,
        "パワー": 75,
        "走力": 37,
        "肩力": 63,
        "守備": 60,
        "捕球": 45,
        "精神力": 47,
        "勝負強さ": 43,
        "安定感": 32,
        "対左": 50,
        "代打": 50,
        "盗塁": 50,
        "走塁": 50,
        "弾道": 4
      }
    },
    {
      "名前": "関根勇人",
      "背番号": 46,
      "年齢": 20,
      "ポジション": "三塁手",
      "外国人": false,
      "年俸": 89040000,
      "プロ年数": 0,
      "ドラフト順位": 0,
      "育成選手": false,
      "チームレベル": "二軍",
      "サブポジション": [],
      "サブポジション評価": {},
      "能力値": {
        "ミート": 69,
        "パワー": 64,
        "走力": 61,
        "肩力": 49,
        "守備": 66,
        "捕球": 38,
        "精神力": 68,
        "勝負強さ": 52,
        "安定感": 30,
        "対左": 50,
        "代打": 50,
        "盗塁": 50,
        "走塁": 50,
        "弾道": 2
      }
    },
    {
      "名前": "磯野修平",
      "背番号": 47,
      "年齢": 27,
      "ポジション": "三塁手",
      "外国人": false,
      "年俸": 90932000,
      "プロ年数": 0,
      "ドラフト順位": 0,
      "育成選手": false,
      "チームレベル": "二軍",
      "サブポジション": [
        "一塁手"
      ],
      "サブポジション評価": {
        "一塁手": 0.6526384809273479
      },
      "能力値": {
        "ミート": 69,
        "パワー": 57,
        "走力": 54,
        "肩力": 39,
        "守備": 63,
        "捕球": 66,
        "精神力": 49,
        "勝負強さ": 61,
        "安定感": 50,
        "対左": 50,
        "代打": 50,
        "盗塁": 50,
        "走塁": 50,
        "弾道": 2
      }
    },
    {
      "名前": "池上健",
      "背番号": 48,
      "年齢": 31,
      "ポジション": "三塁手",
      "外国人": false,
      "年俸": 93534000,
      "プロ年数": 0,
      "ドラフト順位": 0,
      "育成選手": false,
      "チームレベル": "二軍",
      "サブポジション": [
        "一塁手"
      ],
      "サブポジション評価": {
        "一塁手": 0.7429675367534474
      },
      "能力値": {
        "ミート": 63,
        "パワー": 70,
        "走力": 44,
        "肩力": 31,
        "守備": 67,
        "捕球": 48,
        "精神力": 48,
        "勝負強さ": 64,
        "安定感": 36,
        "対左": 50,
        "代打": 50,
        "盗塁": 50,
        "走塁": 50,
        "弾道": 3
      }
    },
    {
      "名前": "金子誠",
      "背番号": 49,
      "年齢": 24,
      "ポジション": "遊撃手",
      "外国人": false,
      "年俸": 78616000,
      "プロ年数": 0,
      "ドラフト順位": 0,
      "育成選手": false,
      "チームレベル": "二軍",
      "サブポジション": [
        "二塁手"
      ],
      "サブポジション評価": {
        "二塁手": 0.689159436445432
      },
      "能力値": {
        "ミート": 66,
        "パワー": 50,
        "走力": 39,
        "肩力": 54,
        "守備": 68,
        "捕球": 66,
        "精神力": 44,
        "勝負強さ": 42,
        "安定感": 31,
        "対左": 50,
        "代打": 50,
        "盗塁": 50,
        "走塁": 50,
        "弾道": 3
      }
    },
    {
      "名前": "天野慎太郎",
      "背番号": 50,
      "年齢": 33,
      "ポジション": "遊撃手",
      "外国人": false,
      "年俸": 71554000,
      "プロ年数": 0,
      "ドラフト順位": 0,
      "育成選手": false,
      "チームレベル": "二軍",
      "サブポジション": [
        "二塁手",
        "三塁手"
      ],
      "サブポジション評価": {
        "二塁手": 0.7900965179378217,
        "三塁手": 0.6013727316486757
      },
      "能力値": {
        "ミート": 42,
        "パワー": 41,
        "走力": 39,
        "肩力": 65,
        "守備": 49,
        "捕球": 66,
        "精神力": 68,
        "勝負強さ": 69,
        "安定感": 38,
        "対左": 50,
        "代打": 50,
        "盗塁": 50,
        "走塁": 50,
        "弾道": 1
      }
    },
    {
      "名前": "熊谷慎太郎",
      "背番号": 51,
      "年齢": 19,
      "ポジション": "遊撃手",
      "外国人": false,
      "年俸": 79254000,
      "プロ年数": 0,
      "ドラフト順位": 0,
      "育成選手": false,
      "チームレベル": "二軍",
      "サブポジション": [
        "三塁手"
      ],
      "サブポジション評価": {
        "三塁手": 0.6382797984453076
      },
      "能力値": {
        "ミート": 75,
        "パワー": 45,
        "走力": 47,
        "肩力": 54,
        "守備": 59,
        "捕球": 35,
        "精神力": 69,
        "勝負強さ": 37,
        "安定感": 49,
        "対左": 50,
        "代打": 50,
        "盗塁": 50,
        "走塁": 50,
        "弾道": 2
      }
    },
    {
      "名前": "秋元蒼",
      "背番号": 52,
      "年齢": 27,
      "ポジション": "遊撃手",
      "外国人": false,
      "年俸": 75311000,
      "プロ年数": 0,
      "ドラフト順位": 0,
      "育成選手": false,
      "チームレベル": "二軍",
      "サブポジション": [],
      "サブポジション評価": {},
      "能力値": {
        "ミート": 54,
        "パワー": 38,
        "走力": 57,
        "肩力": 55,
        "守備": 53,
        "捕球": 39,
        "精神力": 61,
        "勝負強さ": 49,
        "安定感": 48,
        "対左": 50,
        "代打": 50,
        "盗塁": 50,
        "走塁": 50,
        "弾道": 1
      }
    },
    {
      "名前": "池上慎太郎",
      "背番号": 53,
      "年齢": 36,
      "ポジション": "遊撃手",
      "外国人": false,
      "年俸": 88263999,
      "プロ年数": 0,
      "ドラフト順位": 0,
      "育成選手": false,
      "チームレベル": "二軍",
      "サブポジション": [],
      "サブポジション評価": {},
      "能力値": {
        "ミート": 66,
        "パワー": 50,
        "走力": 51,
        "肩力": 34,
        "守備": 45,
        "捕球": 70,
        "精神力": 63,
        "勝負強さ": 33,
        "安定感": 39,
        "対左": 50,
        "代打": 50,
        "盗塁": 50,
        "走塁": 50,
        "弾道": 2
      }
    },
    {
      "名前": "磯野湊",
      "背番号": 54,
      "年齢": 37,
      "ポジション": "遊撃手",
      "外国人": false,
      "年俸": 100147000,
      "プロ年数": 0,
      "ドラフト順位": 0,
      "育成選手": false,
      "チームレベル": "二軍",
      "サブポジション": [
        "二塁手"
      ],
      "サブポジション評価": {
        "二塁手": 0.7087658938198313
      },
      "能力値": {
        "ミート": 74,
        "パワー": 67,
        "走力": 42,
        "肩力": 52,
        "守備": 69,
        "捕球": 39,
        "精神力": 43,
        "勝負強さ": 50,
        "安定感": 54,
        "対左": 50,
        "代打": 50,
        "盗塁": 50,
        "走塁": 50,
        "弾道": 3
      }
    },
    {
      "名前": "瀬戸匠",
      "背番号": 55,
      "年齢": 20,
      "ポジション": "外野手",
      "外国人": false,
      "年俸": 74520000,
      "プロ年数": 0,
      "ドラフト順位": 0,
      "育成選手": false,
      "チームレベル": "二軍",
      "サブポジション": [],
      "サブポジション評価": {},
      "能力値": {
        "ミート": 56,
        "パワー": 50,
        "走力": 47,
        "肩力": 53,
        "守備": 59,
        "捕球": 49,
        "精神力": 63,
        "勝負強さ": 53,
        "安定感": 37,
        "対左": 50,
        "代打": 50,
        "盗塁": 50,
        "走塁": 50,
        "弾道": 2
      }
    },
    {
      "名前": "太田翔太",
      "背番号": 56,
      "年齢": 37,
      "ポジション": "外野手",
      "外国人": false,
      "年俸": 93845000,
      "プロ年数": 0,
      "ドラフト順位": 0,
      "育成選手": false,
      "チームレベル": "二軍",
      "サブポジション": [],
      "サブポジション評価": {},
      "能力値": {
        "ミート": 47,
        "パワー": 75,
        "走力": 55,
        "肩力": 48,
        "守備": 48,
        "捕球": 59,
        "精神力": 42,
        "勝負強さ": 62,
        "安定感": 45,
        "対左": 50,
        "代打": 50,
        "盗塁": 50,
        "走塁": 50,
        "弾道": 3
      }
    },
    {
      "名前": "桑原勇人",
      "背番号": 57,
      "年齢": 38,
      "ポジション": "外野手",
      "外国人": false,
      "年俸": 75486000,
      "プロ年数": 0,
      "ドラフト順位": 0,
      "育成選手": false,
      "チームレベル": "二軍",
      "サブポジション": [],
      "サブポジション評価": {},
      "能力値": {
        "ミート": 42,
        "パワー": 51,
        "走力": 42,
        "肩力": 69,
        "守備": 53,
        "捕球": 55,
        "精神力": 58,
        "勝負強さ": 42,
        "安定感": 64,
        "対左": 50,
        "代打": 50,
        "盗塁": 50,
        "走塁": 50,
        "弾道": 2
      }
    },
    {
      "名前": "篠原颯",
      "背番号": 58,
      "年齢": 21,
      "ポジション": "外野手",
      "外国人": false,
      "年俸": 92928000,
      "プロ年数": 0,
      "ドラフト順位": 0,
      "育成選手": false,
      "チームレベル": "二軍",
      "サブポジション": [],
      "サブポジション評価": {},
      "能力値": {
        "ミート": 75,
        "パワー": 71,
        "走力": 55,
        "肩力": 59,
        "守備": 69,
        "捕球": 68,
        "精神力": 32,
        "勝負強さ": 45,
        "安定感": 32,
        "対左": 50,
        "代打": 50,
        "盗塁": 50,
        "走塁": 50,
        "弾道": 4
      }
    },
    {
      "名前": "尾崎亮太",
      "背番号": 59,
      "年齢": 20,
      "ポジション": "外野手",
      "外国人": false,
      "年俸": 78960000,
      "プロ年数": 0,
      "ドラフト順位": 0,
      "育成選手": false,
      "チームレベル": "二軍",
      "サブポジション": [
        "一塁手",
        "三塁手"
      ],
      "サブポジション評価": {
        "一塁手": 0.7123774603877018,
        "三塁手": 0.40032463960127024
      },
      "能力値": {
        "ミート": 52,
        "パワー": 75,
        "走力": 44,
        "肩力": 48,
        "守備": 63,
        "捕球": 70,
        "精神力": 46,
        "勝負強さ": 37,
        "安定感": 49,
        "対左": 50,
        "代打": 50,
        "盗塁": 50,
        "走塁": 50,
        "弾道": 4
      }
    },
    {
      "名前": "白石康平",
      "背番号": 60,
      "年齢": 21,
      "ポジション": "外野手",
      "外国人": false,
      "年俸": 68244000,
      "プロ年数": 0,
      "ドラフト順位": 0,
      "育成選手": false,
      "チームレベル": "二軍",
      "サブポジション": [],
      "サブポジション評価": {},
      "能力値": {
        "ミート": 51,
        "パワー": 47,
        "走力": 43,
        "肩力": 67,
        "守備": 49,
        "捕球": 36,
        "精神力": 41,
        "勝負強さ": 33,
        "安定感": 35,
        "対左": 50,
        "代打": 50,
        "盗塁": 50,
        "走塁": 50,
        "弾道": 1
      }
    },
    {
      "名前": "関根勇気",
      "背番号": 61,
      "年齢": 30,
      "ポジション": "外野手",
      "外国人": false,
      "年俸": 84760000,
      "プロ年数": 0,
      "ドラフト順位": 0,
      "育成選手": false,
      "チームレベル": "二軍",
      "サブポジション": [],
      "サブポジション評価": {},
      "能力値": {
        "ミート": 73,
        "パワー": 42,
        "走力": 40,
        "肩力": 59,
        "守備": 58,
        "捕球": 59,
        "精神力": 64,
        "勝負強さ": 54,
        "安定感": 65,
        "対左": 50,
        "代打": 50,
        "盗塁": 50,
        "走塁": 50,
        "弾道": 1
      }
    },
    {
      "名前": "滝沢海斗",
      "背番号": 62,
      "年齢": 28,
      "ポジション": "外野手",
      "外国人": false,
      "年俸": 80768000,
      "プロ年数": 0,
      "ドラフト順位": 0,
      "育成選手": false,
      "チームレベル": "二軍",
      "サブポジション": [
        "三塁手"
      ],
      "サブポジション評価": {
        "三塁手": 0.5488675455865423
      },
      "能力値": {
        "ミート": 42,
        "パワー": 51,
        "走力": 72,
        "肩力": 30,
        "守備": 44,
        "捕球": 57,
        "精神力": 63,
        "勝負強さ": 66,
        "安定感": 43,
        "対左": 50,
        "代打": 50,
        "盗塁": 50,
        "走塁": 50,
        "弾道": 2
      }
    },
    {
      "名前": "小野寺悠斗",
      "背番号": 63,
      "年齢": 31,
      "ポジション": "外野手",
      "外国人": false,
      "年俸": 88032000,
      "プロ年数": 0,
      "ドラフト順位": 0,
      "育成選手": false,
      "チームレベル": "二軍",
      "サブポジション": [],
      "サブポジション評価": {},
      "能力値": {
        "ミート": 42,
        "パワー": 75,
        "走力": 73,
        "肩力": 57,
        "守備": 66,
        "捕球": 63,
        "精神力": 43,
        "勝負強さ": 33,
        "安定感": 45,
        "対左": 50,
        "代打": 50,
        "盗塁": 50,
        "走塁": 50,
        "弾道": 4
      }
    },
    {
      "名前": "熊谷健",
      "背番号": 64,
      "年齢": 30,
      "ポジション": "外野手",
      "外国人": false,
      "年俸": 88920000,
      "プロ年数": 0,
      "ドラフト順位": 0,
      "育成選手": false,
      "チームレベル": "二軍",
      "サブポジション": [
        "一塁手"
      ],
      "サブポジション評価": {
        "一塁手": 0.5971859668633128
      },
      "能力値": {
        "ミート": 54,
        "パワー": 65,
        "走力": 57,
        "肩力": 33,
        "守備": 55,
        "捕球": 53,
        "精神力": 44,
        "勝負強さ": 59,
        "安定感": 45,
        "対左": 50,
        "代打": 50,
        "盗塁": 50,
        "走塁": 50,
        "弾道": 2
      }
    },
    {
      "名前": "杉山誠",
      "背番号": 65,
      "年齢": 26,
      "ポジション": "外野手",
      "外国人": false,
      "年俸": 68543999,
      "プロ年数": 0,
      "ドラフト順位": 0,
      "育成選手": false,
      "チームレベル": "二軍",
      "サブポジション": [],
      "サブポジション評価": {},
      "能力値": {
        "ミート": 43,
        "パワー": 42,
        "走力": 52,
        "肩力": 59,
        "守備": 53,
        "捕球": 45,
        "精神力": 56,
        "勝負強さ": 42,
        "安定感": 36,
        "対左": 50,
        "代打": 50,
        "盗塁": 50,
        "走塁": 50,
        "弾道": 2
      }
    },
    {
      "名前": "木下悠斗",
      "背番号": 66,
      "年齢": 19,
      "ポジション": "外野手",
      "外国人": false,
      "年俸": 79968000,
      "プロ年数": 0,
      "ドラフト順位": 0,
      "育成選手": false,
      "チームレベル": "二軍",
      "サブポジション": [],
      "サブポジション評価": {},
      "能力値": {
        "ミート": 51,
        "パワー": 52,
        "走力": 71,
        "肩力": 30,
        "守備": 56,
        "捕球": 44,
        "精神力": 41,
        "勝負強さ": 70,
        "安定感": 63,
        "対左": 50,
        "代打": 50,
        "盗塁": 50,
        "走塁": 50,
        "弾道": 2
      }
    },
    {
      "名前": "小野寺健太",
      "背番号": 67,
      "年齢": 19,
      "ポジション": "外野手",
      "外国人": false,
      "年俸": 81158000,
      "プロ年数": 0,
      "ドラフト順位": 0,
      "育成選手": false,
      "チームレベル": "二軍",
      "サブポジション": [],
      "サブポジション評価": {},
      "能力値": {
        "ミート": 69,
        "パワー": 50,
        "走力": 52,
        "肩力": 47,
        "守備": 36,
        "捕球": 36,
        "精神力": 50,
        "勝負強さ": 52,
        "安定感": 30,
        "対左": 50,
        "代打": 50,
        "盗塁": 50,
        "走塁": 50,
        "弾道": 2
      }
    },
    {
      "名前": "岩崎優",
      "背番号": 68,
      "年齢": 38,
      "ポジション": "外野手",
      "外国人": false,
      "年俸": 80040000,
      "プロ年数": 0,
      "ドラフト順位": 0,
      "育成選手": false,
      "チームレベル": "二軍",
      "サブポジション": [
        "一塁手",
        "三塁手"
      ],
      "サブポジション評価": {
        "一塁手": 0.6271814535370774,
        "三塁手": 0.46863689681573
      },
      "能力値": {
        "ミート": 48,
        "パワー": 35,
        "走力": 73,
        "肩力": 62,
        "守備": 58,
        "捕球": 52,
        "精神力": 32,
        "勝負強さ": 37,
        "安定感": 66,
        "対左": 50,
        "代打": 50,
        "盗塁": 50,
        "走塁": 50,
        "弾道": 2
      }
    },
    {
      "名前": "海老原修平",
      "背番号": 69,
      "年齢": 32,
      "ポジション": "外野手",
      "外国人": false,
      "年俸": 74052000,
      "プロ年数": 0,
      "ドラフト順位": 0,
      "育成選手": false,
      "チームレベル": "二軍",
      "サブポジション": [],
      "サブポジション評価": {},
      "能力値": {
        "ミート": 49,
        "パワー": 38,
        "走力": 42,
        "肩力": 49,
        "守備": 60,
        "捕球": 64,
        "精神力": 30,
        "勝負強さ": 67,
        "安定感": 47,
        "対左": 50,
        "代打": 50,
        "盗塁": 50,
        "走塁": 50,
        "弾道": 1
      }
    },
    {
      "名前": "木下陸",
      "背番号": 70,
      "年齢": 27,
      "ポジション": "外野手",
      "外国人": false,
      "年俸": 84709000,
      "プロ年数": 0,
      "ドラフト順位": 0,
      "育成選手": false,
      "チームレベル": "二軍",
      "サブポジション": [],
      "サブポジション評価": {},
      "能力値": {
        "ミート": 60,
        "パワー": 52,
        "走力": 56,
        "肩力": 68,
        "守備": 60,
        "捕球": 57,
        "精神力": 48,
        "勝負強さ": 59,
        "安定感": 48,
        "対左": 50,
        "代打": 50,
        "盗塁": 50,
        "走塁": 50,
        "弾道": 3
      }
    },
    {
      "名前": "有馬悠斗",
      "背番号": 101,
      "年齢": 35,
      "ポジション": "投手",
      "外国人": false,
      "年俸": 66876923,
      "プロ年数": 0,
      "ドラフト順位": 0,
      "育成選手": true,
      "チームレベル": "三軍",
      "球種": "中継ぎ",
      "先発適性": 32,
      "中継ぎ適性": 98,
      "抑え適性": 45,
      "能力値": {
        "球速": 27,
        "コントロール": 33,
        "スタミナ": 35,
        "変化球": 34,
        "精神力": 25,
        "安定感": 50,
        "対左": 50,
        "持ち球": [
          "シュート",
          "カーブ",
          "フォーク"
        ],
        "決め球": "フォーク",
        "球種レパートリー": {}
      }
    },
    {
      "名前": "太田健太",
      "背番号": 102,
      "年齢": 34,
      "ポジション": "投手",
      "外国人": false,
      "年俸": 68443076,
      "プロ年数": 0,
      "ドラフト順位": 0,
      "育成選手": true,
      "チームレベル": "三軍",
      "球種": "中継ぎ",
      "先発適性": 45,
      "中継ぎ適性": 94,
      "抑え適性": 47,
      "能力値": {
        "球速": 36,
        "コントロール": 28,
        "スタミナ": 45,
        "変化球": 36,
        "精神力": 29,
        "安定感": 50,
        "対左": 50,
        "持ち球": [
          "チェンジアップ",
          "Hシンカー"
        ],
        "決め球": "チェンジアップ",
        "球種レパートリー": {}
      }
    },
    {
      "名前": "石橋圭介",
      "背番号": 103,
      "年齢": 20,
      "ポジション": "投手",
      "外国人": false,
      "年俸": 67107692,
      "プロ年数": 0,
      "ドラフト順位": 0,
      "育成選手": true,
      "チームレベル": "三軍",
      "球種": "先発",
      "先発適性": 97,
      "中継ぎ適性": 51,
      "抑え適性": 29,
      "能力値": {
        "球速": 30,
        "コントロール": 38,
        "スタミナ": 26,
        "変化球": 38,
        "精神力": 50,
        "安定感": 50,
        "対左": 50,
        "持ち球": [
          "ツーシーム",
          "スプリット",
          "フォーク"
        ],
        "決め球": "ツーシーム",
        "球種レパートリー": {}
      }
    },
    {
      "名前": "池上健太",
      "背番号": 104,
      "年齢": 25,
      "ポジション": "投手",
      "外国人": false,
      "年俸": 68653846,
      "プロ年数": 0,
      "ドラフト順位": 0,
      "育成選手": true,
      "チームレベル": "三軍",
      "球種": "中継ぎ",
      "先発適性": 39,
      "中継ぎ適性": 89,
      "抑え適性": 51,
      "能力値": {
        "球速": 33,
        "コントロール": 40,
        "スタミナ": 34,
        "変化球": 44,
        "精神力": 31,
        "安定感": 50,
        "対左": 50,
        "持ち球": [
          "Hシンカー",
          "チェンジアップ",
          "カーブ",
          "シンカー"
        ],
        "決め球": "Hシンカー",
        "球種レパートリー": {}
      }
    },
    {
      "名前": "桜井大輝",
      "背番号": 105,
      "年齢": 34,
      "ポジション": "投手",
      "外国人": false,
      "年俸": 60196923,
      "プロ年数": 0,
      "ドラフト順位": 0,
      "育成選手": true,
      "チームレベル": "三軍",
      "球種": "先発",
      "先発適性": 98,
      "中継ぎ適性": 45,
      "抑え適性": 43,
      "能力値": {
        "球速": 27,
        "コントロール": 26,
        "スタミナ": 31,
        "変化球": 35,
        "精神力": 27,
        "安定感": 50,
        "対左": 50,
        "持ち球": [
          "スライダー",
          "フォーク"
        ],
        "決め球": "スライダー",
        "球種レパートリー": {}
      }
    },
    {
      "名前": "有馬健",
      "背番号": 106,
      "年齢": 20,
      "ポジション": "投手",
      "外国人": false,
      "年俸": 60553846,
      "プロ年数": 0,
      "ドラフト順位": 0,
      "育成選手": true,
      "チームレベル": "三軍",
      "球種": "先発",
      "先発適性": 97,
      "中継ぎ適性": 39,
      "抑え適性": 40,
      "能力値": {
        "球速": 35,
        "コントロール": 27,
        "スタミナ": 24,
        "変化球": 28,
        "精神力": 36,
        "安定感": 50,
        "対左": 50,
        "持ち球": [
          "カーブ",
          "フォーク"
        ],
        "決め球": "フォーク",
        "球種レパートリー": {}
      }
    },
    {
      "名前": "杉山大輝",
      "背番号": 107,
      "年齢": 37,
      "ポジション": "投手",
      "外国人": false,
      "年俸": 74401538,
      "プロ年数": 0,
      "ドラフト順位": 0,
      "育成選手": true,
      "チームレベル": "三軍",
      "球種": "中継ぎ",
      "先発適性": 27,
      "中継ぎ適性": 99,
      "抑え適性": 70,
      "能力値": {
        "球速": 37,
        "コントロール": 41,
        "スタミナ": 42,
        "変化球": 39,
        "精神力": 28,
        "安定感": 50,
        "対左": 50,
        "持ち球": [
          "フォーク"
        ],
        "決め球": "フォーク",
        "球種レパートリー": {}
      }
    },
    {
      "名前": "内山勇人",
      "背番号": 108,
      "年齢": 27,
      "ポジション": "投手",
      "外国人": false,
      "年俸": 70338461,
      "プロ年数": 0,
      "ドラフト順位": 0,
      "育成選手": true,
      "チームレベル": "三軍",
      "球種": "中継ぎ",
      "先発適性": 33,
      "中継ぎ適性": 80,
      "抑え適性": 63,
      "能力値": {
        "球速": 33,
        "コントロール": 30,
        "スタミナ": 36,
        "変化球": 37,
        "精神力": 38,
        "安定感": 50,
        "対左": 50,
        "持ち球": [
          "チェンジアップ",
          "シュート",
          "シンカー"
        ],
        "決め球": "チェンジアップ",
        "球種レパートリー": {}
      }
    },
    {
      "名前": "内山誠",
      "背番号": 109,
      "年齢": 20,
      "ポジション": "投手",
      "外国人": false,
      "年俸": 66000000,
      "プロ年数": 0,
      "ドラフト順位": 0,
      "育成選手": true,
      "チームレベル": "三軍",
      "球種": "先発",
      "先発適性": 87,
      "中継ぎ適性": 36,
      "抑え適性": 37,
      "能力値": {
        "球速": 37,
        "コントロール": 29,
        "スタミナ": 39,
        "変化球": 33,
        "精神力": 38,
        "安定感": 50,
        "対左": 50,
        "持ち球": [
          "スライダー",
          "シュート",
          "カーブ"
        ],
        "決め球": "スライダー",
        "球種レパートリー": {}
      }
    },
    {
      "名前": "越智健太",
      "背番号": 110,
      "年齢": 30,
      "ポジション": "投手",
      "外国人": false,
      "年俸": 62900000,
      "プロ年数": 0,
      "ドラフト順位": 0,
      "育成選手": true,
      "チームレベル": "三軍",
      "球種": "中継ぎ",
      "先発適性": 45,
      "中継ぎ適性": 98,
      "抑え適性": 59,
      "能力値": {
        "球速": 35,
        "コントロール": 22,
        "スタミナ": 27,
        "変化球": 26,
        "精神力": 47,
        "安定感": 50,
        "対左": 50,
        "持ち球": [
          "カーブ"
        ],
        "決め球": "カーブ",
        "球種レパートリー": {}
      }
    },
    {
      "名前": "赤井駿",
      "背番号": 111,
      "年齢": 34,
      "ポジション": "投手",
      "外国人": false,
      "年俸": 69473846,
      "プロ年数": 0,
      "ドラフト順位": 0,
      "育成選手": true,
      "チームレベル": "三軍",
      "球種": "抑え",
      "先発適性": 36,
      "中継ぎ適性": 56,
      "抑え適性": 83,
      "能力値": {
        "球速": 28,
        "コントロール": 32,
        "スタミナ": 26,
        "変化球": 42,
        "精神力": 47,
        "安定感": 50,
        "対左": 50,
        "持ち球": [
          "スプリット",
          "縦カーブ",
          "カーブ",
          "フォーク"
        ],
        "決め球": "スプリット",
        "球種レパートリー": {}
      }
    },
    {
      "名前": "石橋大輝",
      "背番号": 112,
      "年齢": 25,
      "ポジション": "投手",
      "外国人": false,
      "年俸": 62788461,
      "プロ年数": 0,
      "ドラフト順位": 0,
      "育成選手": true,
      "チームレベル": "三軍",
      "球種": "中継ぎ",
      "先発適性": 31,
      "中継ぎ適性": 84,
      "抑え適性": 44,
      "能力値": {
        "球速": 30,
        "コントロール": 31,
        "スタミナ": 22,
        "変化球": 33,
        "精神力": 33,
        "安定感": 50,
        "対左": 50,
        "持ち球": [
          "Hシンカー",
          "チェンジアップ",
          "カーブ"
        ],
        "決め球": "チェンジアップ",
        "球種レパートリー": {}
      }
    },
    {
      "名前": "島田大和",
      "背番号": 113,
      "年齢": 25,
      "ポジション": "遊撃手",
      "外国人": false,
      "年俸": 63125000,
      "プロ年数": 0,
      "ドラフト順位": 0,
      "育成選手": true,
      "チームレベル": "三軍",
      "サブポジション": [
        "三塁手"
      ],
      "サブポジション評価": {
        "三塁手": 0.7080749252503733
      },
      "能力値": {
        "ミート": 21,
        "パワー": 39,
        "走力": 26,
        "肩力": 22,
        "守備": 30,
        "捕球": 26,
        "精神力": 33,
        "勝負強さ": 46,
        "安定感": 30,
        "対左": 50,
        "代打": 50,
        "盗塁": 50,
        "走塁": 50,
        "弾道": 3
      }
    },
    {
      "名前": "秋元健太",
      "背番号": 114,
      "年齢": 35,
      "ポジション": "遊撃手",
      "外国人": false,
      "年俸": 59939999,
      "プロ年数": 0,
      "ドラフト順位": 0,
      "育成選手": true,
      "チームレベル": "三軍",
      "サブポジション": [
        "二塁手"
      ],
      "サブポジション評価": {
        "二塁手": 0.7038578992895506
      },
      "能力値": {
        "ミート": 32,
        "パワー": 24,
        "走力": 28,
        "肩力": 32,
        "守備": 41,
        "捕球": 35,
        "精神力": 34,
        "勝負強さ": 48,
        "安定感": 33,
        "対左": 50,
        "代打": 50,
        "盗塁": 50,
        "走塁": 50,
        "弾道": 1
      }
    },
    {
      "名前": "桑原健太",
      "背番号": 115,
      "年齢": 37,
      "ポジション": "外野手",
      "外国人": false,
      "年俸": 66445000,
      "プロ年数": 0,
      "ドラフト順位": 0,
      "育成選手": true,
      "チームレベル": "三軍",
      "サブポジション": [
        "一塁手"
      ],
      "サブポジション評価": {
        "一塁手": 0.6550319700295456
      },
      "能力値": {
        "ミート": 26,
        "パワー": 40,
        "走力": 37,
        "肩力": 30,
        "守備": 23,
        "捕球": 31,
        "精神力": 48,
        "勝負強さ": 29,
        "安定感": 27,
        "対左": 50,
        "代打": 50,
        "盗塁": 50,
        "走塁": 50,
        "弾道": 2
      }
    },
    {
      "名前": "青山航",
      "背番号": 116,
      "年齢": 23,
      "ポジション": "二塁手",
      "外国人": false,
      "年俸": 62484000,
      "プロ年数": 0,
      "ドラフト順位": 0,
      "育成選手": true,
      "チームレベル": "三軍",
      "サブポジション": [
        "遊撃手",
        "三塁手"
      ],
      "サブポジション評価": {
        "遊撃手": 0.7033363613661084,
        "三塁手": 0.5425530881889521
      },
      "能力値": {
        "ミート": 41,
        "パワー": 27,
        "走力": 46,
        "肩力": 26,
        "守備": 23,
        "捕球": 31,
        "精神力": 38,
        "勝負強さ": 21,
        "安定感": 23,
        "対左": 50,
        "代打": 50,
        "盗塁": 50,
        "走塁": 50,
        "弾道": 1
      }
    },
    {
      "名前": "白石健",
      "背番号": 117,
      "年齢": 29,
      "ポジション": "二塁手",
      "外国人": false,
      "年俸": 73788000,
      "プロ年数": 0,
      "ドラフト順位": 0,
      "育成選手": true,
      "チームレベル": "三軍",
      "サブポジション": [
        "遊撃手"
      ],
      "サブポジション評価": {
        "遊撃手": 0.6191092128799416
      },
      "能力値": {
        "ミート": 41,
        "パワー": 32,
        "走力": 31,
        "肩力": 26,
        "守備": 26,
        "捕球": 25,
        "精神力": 22,
        "勝負強さ": 48,
        "安定感": 47,
        "対左": 50,
        "代打": 50,
        "盗塁": 50,
        "走塁": 50,
        "弾道": 1
      }
    },
    {
      "名前": "飯田海斗",
      "背番号": 118,
      "年齢": 19,
      "ポジション": "外野手",
      "外国人": false,
      "年俸": 62356000,
      "プロ年数": 0,
      "ドラフト順位": 0,
      "育成選手": true,
      "チームレベル": "三軍",
      "サブポジション": [],
      "サブポジション評価": {},
      "能力値": {
        "ミート": 29,
        "パワー": 45,
        "走力": 41,
        "肩力": 36,
        "守備": 38,
        "捕球": 30,
        "精神力": 36,
        "勝負強さ": 47,
        "安定感": 31,
        "対左": 50,
        "代打": 50,
        "盗塁": 50,
        "走塁": 50,
        "弾道": 3
      }
    },
    {
      "名前": "小池陽太",
      "背番号": 119,
      "年齢": 30,
      "ポジション": "外野手",
      "外国人": false,
      "年俸": 63180000,
      "プロ年数": 0,
      "ドラフト順位": 0,
      "育成選手": true,
      "チームレベル": "三軍",
      "サブポジション": [
        "一塁手"
      ],
      "サブポジション評価": {
        "一塁手": 0.6609081417059135
      },
      "能力値": {
        "ミート": 29,
        "パワー": 26,
        "走力": 44,
        "肩力": 21,
        "守備": 24,
        "捕球": 35,
        "精神力": 32,
        "勝負強さ": 33,
        "安定感": 47,
        "対左": 50,
        "代打": 50,
        "盗塁": 50,
        "走塁": 50,
        "弾道": 1
      }
    },
    {
      "名前": "遠藤圭介",
      "背番号": 120,
      "年齢": 34,
      "ポジション": "外野手",
      "外国人": false,
      "年俸": 74236000,
      "プロ年数": 0,
      "ドラフト順位": 0,
      "育成選手": true,
      "チームレベル": "三軍",
      "サブポジション": [
        "一塁手"
      ],
      "サブポジション評価": {
        "一塁手": 0.6289384228491988
      },
      "能力値": {
        "ミート": 37,
        "パワー": 36,
        "走力": 24,
        "肩力": 21,
        "守備": 33,
        "捕球": 49,
        "精神力": 45,
        "勝負強さ": 41,
        "安定感": 48,
        "対左": 50,
        "代打": 50,
        "盗塁": 50,
        "走塁": 50,
        "弾道": 1
      }
    },
    {
      "名前": "上田康平",
      "背番号": 121,
      "年齢": 37,
      "ポジション": "捕手",
      "外国人": false,
      "年俸": 62198000,
      "プロ年数": 0,
      "ドラフト順位": 0,
      "育成選手": true,
      "チームレベル": "三軍",
      "サブポジション": [],
      "サブポジション評価": {},
      "能力値": {
        "ミート": 33,
        "パワー": 20,
        "走力": 36,
        "肩力": 38,
        "守備": 31,
        "捕球": 31,
        "精神力": 48,
        "勝負強さ": 31,
        "安定感": 35,
        "対左": 50,
        "代打": 50,
        "盗塁": 50,
        "走塁": 50,
        "弾道": 2
      }
    },
    {
      "名前": "浅野勇人",
      "背番号": 122,
      "年齢": 26,
      "ポジション": "二塁手",
      "外国人": false,
      "年俸": 66654000,
      "プロ年数": 0,
      "ドラフト順位": 0,
      "育成選手": true,
      "チームレベル": "三軍",
      "サブポジション": [
        "遊撃手"
      ],
      "サブポジション評価": {
        "遊撃手": 0.6378580615745304
      },
      "能力値": {
        "ミート": 37,
        "パワー": 43,
        "走力": 24,
        "肩力": 17,
        "守備": 38,
        "捕球": 49,
        "精神力": 48,
        "勝負強さ": 33,
        "安定感": 44,
        "対左": 50,
        "代打": 50,
        "盗塁": 50,
        "走塁": 50,
        "弾道": 2
      }
    },
    {
      "名前": "岩崎拓海",
      "背番号": 123,
      "年齢": 30,
      "ポジション": "外野手",
      "外国人": false,
      "年俸": 69550000,
      "プロ年数": 0,
      "ドラフト順位": 0,
      "育成選手": true,
      "チームレベル": "三軍",
      "サブポジション": [],
      "サブポジション評価": {},
      "能力値": {
        "ミート": 39,
        "パワー": 41,
        "走力": 21,
        "肩力": 27,
        "守備": 28,
        "捕球": 36,
        "精神力": 22,
        "勝負強さ": 41,
        "安定感": 39,
        "対左": 50,
        "代打": 50,
        "盗塁": 50,
        "走塁": 50,
        "弾道": 2
      }
    },
    {
      "名前": "青山慎太郎",
      "背番号": 124,
      "年齢": 28,
      "ポジション": "外野手",
      "外国人": false,
      "年俸": 65536000,
      "プロ年数": 0,
      "ドラフト順位": 0,
      "育成選手": true,
      "チームレベル": "三軍",
      "サブポジション": [],
      "サブポジション評価": {},
      "能力値": {
        "ミート": 41,
        "パワー": 37,
        "走力": 24,
        "肩力": 34,
        "守備": 23,
        "捕球": 29,
        "精神力": 24,
        "勝負強さ": 42,
        "安定感": 28,
        "対左": 50,
        "代打": 50,
        "盗塁": 50,
        "走塁": 50,
        "弾道": 1
      }
    },
    {
      "名前": "荒木翼",
      "背番号": 125,
      "年齢": 24,
      "ポジション": "外野手",
      "外国人": false,
      "年俸": 63116000,
      "プロ年数": 0,
      "ドラフト順位": 0,
      "育成選手": true,
      "チームレベル": "三軍",
      "サブポジション": [],
      "サブポジション評価": {},
      "能力値": {
        "ミート": 41,
        "パワー": 22,
        "走力": 47,
        "肩力": 24,
        "守備": 27,
        "捕球": 37,
        "精神力": 50,
        "勝負強さ": 35,
        "安定感": 37,
        "対左": 50,
        "代打": 50,
        "盗塁": 50,
        "走塁": 50,
        "弾道": 1
      }
    },
    {
      "名前": "遠藤雄大",
      "背番号": 126,
      "年齢": 35,
      "ポジション": "三塁手",
      "外国人": false,
      "年俸": 68445000,
      "プロ年数": 0,
      "ドラフト順位": 0,
      "育成選手": true,
      "チームレベル": "三軍",
      "サブポジション": [],
      "サブポジション評価": {},
      "能力値": {
        "ミート": 35,
        "パワー": 24,
        "走力": 46,
        "肩力": 31,
        "守備": 33,
        "捕球": 25,
        "精神力": 34,
        "勝負強さ": 42,
        "安定感": 49,
        "対左": 50,
        "代打": 50,
        "盗塁": 50,
        "走塁": 50,
        "弾道": 2
      }
    },
    {
      "名前": "熊谷大樹",
      "背番号": 127,
      "年齢": 30,
      "ポジション": "捕手",
      "外国人": false,
      "年俸": 66690000,
      "プロ年数": 0,
      "ドラフト順位": 0,
      "育成選手": true,
      "チームレベル": "三軍",
      "サブポジション": [],
      "サブポジション評価": {},
      "能力値": {
        "ミート": 24,
        "パワー": 42,
        "走力": 31,
        "肩力": 39,
        "守備": 35,
        "捕球": 30,
        "精神力": 40,
        "勝負強さ": 43,
        "安定感": 49,
        "対左": 50,
        "代打": 50,
        "盗塁": 50,
        "走塁": 50,
        "弾道": 3
      }
    },
    {
      "名前": "国分陽太",
      "背番号": 128,
      "年齢": 31,
      "ポジション": "外野手",
      "外国人": false,
      "年俸": 64452000,
      "プロ年数": 0,
      "ドラフト順位": 0,
      "育成選手": true,
      "チームレベル": "三軍",
      "サブポジション": [],
      "サブポジション評価": {},
      "能力値": {
        "ミート": 22,
        "パワー": 34,
        "走力": 35,
        "肩力": 29,
        "守備": 25,
        "捕球": 26,
        "精神力": 35,
        "勝負強さ": 29,
        "安定感": 50,
        "対左": 50,
        "代打": 50,
        "盗塁": 50,
        "走塁": 50,
        "弾道": 2
      }
    },
    {
      "名前": "黒田健",
      "背番号": 129,
      "年齢": 33,
      "ポジション": "外野手",
      "外国人": false,
      "年俸": 59850000,
      "プロ年数": 0,
      "ドラフト順位": 0,
      "育成選手": true,
      "チームレベル": "三軍",
      "サブポジション": [
        "三塁手"
      ],
      "サブポジション評価": {
        "三塁手": 0.42238449341348916
      },
      "能力値": {
        "ミート": 25,
        "パワー": 32,
        "走力": 33,
        "肩力": 20,
        "守備": 41,
        "捕球": 41,
        "精神力": 31,
        "勝負強さ": 36,
        "安定感": 44,
        "対左": 50,
        "代打": 50,
        "盗塁": 50,
        "走塁": 50,
        "弾道": 2
      }
    },
    {
      "名前": "奥田陽翔",
      "背番号": 130,
      "年齢": 32,
      "ポジション": "外野手",
      "外国人": false,
      "年俸": 65207999,
      "プロ年数": 0,
      "ドラフト順位": 0,
      "育成選手": true,
      "チームレベル": "三軍",
      "サブポジション": [],
      "サブポジション評価": {},
      "能力値": {
        "ミート": 30,
        "パワー": 32,
        "走力": 42,
        "肩力": 32,
        "守備": 34,
        "捕球": 35,
        "精神力": 43,
        "勝負強さ": 31,
        "安定感": 26,
        "対左": 50,
        "代打": 50,
        "盗塁": 50,
        "走塁": 50,
        "弾道": 1
      }
    }
  ]
}